dmcm
