Metadata-Version: 1.1
Name: django-dmcm
Version: 1.1.4
Summary: Django Markdown Content Manager.
Home-page: https://github.com/ahernp/DMCM
Author: Paul Ahern
Author-email: ahernp@ahernp.com
License: BSD License
Platform: UNKNOWN
Classifier: Environment :: Web Environment
Classifier: Framework :: Django
Classifier: Intended Audience :: Developers
Classifier: License :: OSI Approved :: BSD License
Classifier: Operating System :: OS Independent
Classifier: Programming Language :: Python
Classifier: Programming Language :: Python :: 2.7
Classifier: Topic :: Internet :: WWW/HTTP
Classifier: Topic :: Internet :: WWW/HTTP :: Dynamic Content
